[{"id":"P1","name":"Имя документа","weight":"1","tolerance":"0","value":"empty"},
{"id":"P2","name":"Название детали","weight":"1","tolerance":"0","value":"empty"},
{"id":"P3","name":"Материал","weight":"1","tolerance":"0","value":"empty"},
{"id":"P4","name":"Дата создания фаила","weight":"1","tolerance":"0","value":"empty"},
{"id":"P5","name":"Дата изменения фаила","weight":"1","tolerance":"0","value":"empty"},
{"id":"P6","name":"Деталь твердотельная (не поверхности)","weight":"1","tolerance":"0","value":"empty"},
{"id":"P7","name":"Деталь состоит из одного твердого тела","weight":"1","tolerance":"0","value":"empty"},
{"id":"P8","name":"Все эскизы (2D и 3D) и объекты вспомогательной геометрии (плоскости, оси, точки) невидимы","weight":"1","tolerance":"0","value":"empty"},
{"id":"P9","name":"Все эскизы детали должны быть полностью определены","weight":"1","tolerance":"0","value":"empty"},
{"id":"P10","name":"Масса детали","weight":"1","tolerance":"0.5","value":"empty"},
{"id":"P11","name":"Площадь детали","weight":"1","tolerance":"0.5","value":"empty"},
{"id":"P12","name":"Объем детали","weight":"1","tolerance":"0.5","value":"empty"},
{"id":"D1","name":"Выбор формата листа","weight":"1","tolerance":"0","value":"empty"},
{"id":"D2","name":"Выбор масштаба главного вида","weight":"1","tolerance":"0","value":"empty"},
{"id":"D3","name":"Заполнение основной надписи","weight":"1","tolerance":"0","value":"empty"}]